README.md
setup.py
server/__init__.py
server/server.py
stripe_asgi_server.egg-info/PKG-INFO
stripe_asgi_server.egg-info/SOURCES.txt
stripe_asgi_server.egg-info/dependency_links.txt
stripe_asgi_server.egg-info/not-zip-safe
stripe_asgi_server.egg-info/requires.txt
stripe_asgi_server.egg-info/top_level.txt