Metadata-Version: 2.1
Name: stripe-asgi-server
Version: 0.0.2
Summary: An asgi server for stripe payments
Home-page: https://github.com/cglacet/stripe-asgi-server
Author: Christian Glacet
Author-email: cglacet@kune.tech
License: MIT
Project-URL: Bug Reports, https://github.com/cglacet/stripe-asgi-server/issues
Project-URL: Source, https://github.com/cglacet/stripe-asgi-server
Platform: UNKNOWN
Classifier: Development Status :: 1 - Planning
Classifier: Programming Language :: Python :: 3
Classifier: Programming Language :: Python :: 3.4
Classifier: Programming Language :: Python :: 3.5
Classifier: Programming Language :: Python :: 3.6
Classifier: Programming Language :: Python :: 3.7
Classifier: Programming Language :: Python :: 3.8
Classifier: Intended Audience :: Developers
Classifier: License :: OSI Approved :: MIT License
Classifier: Operating System :: OS Independent
